AuthProxyApp/__init__.py
AuthProxyApp/asgi.py
AuthProxyApp/settings.py
AuthProxyApp/urls.py
AuthProxyApp/wsgi.py
auth_proxy/__init__.py
auth_proxy/admin.py
auth_proxy/apps.py
auth_proxy/middleware.py
auth_proxy/models.py
auth_proxy/routers.py
auth_proxy/tests.py
auth_proxy/urls.py
auth_proxy/utils.py
auth_proxy/views.py
auth_proxy/migrations/0001_initial.py
auth_proxy/migrations/__init__.py
django_user_proxy-1.2.6.dist-info/LICENSE
django_user_proxy-1.2.6.dist-info/METADATA
django_user_proxy-1.2.6.dist-info/WHEEL
django_user_proxy-1.2.6.dist-info/top_level.txt
django_user_proxy-1.2.6.dist-info/RECORD
